{
    "APP_NAME_CN_ANDROID": "儿童水果猜猜乐",
    "APP_NAME_EN_ANDROID": "KidsGuessFruit",
    "APP_NAME_CN_IOS": "儿童水果猜猜乐",
    "APP_NAME_EN_IOS": "KidsGuessFruit",
    "PACKAGE_ANDROID": "com.moonma.caicailefruit",
    "PACKAGE_IOS": "com.moonma.caicailefruit",
    "APPVERSION_ANDROID": "1.0.2",
    "APPVERSION_CODE_ANDROID": "102",
    "APPVERSION_IOS": "1.0.2",
    "need_upload_screenshot": false,
    "APPSTORE_VERSION_UPDATE": {
        "cn": "修复闪退",
        "en": "Fix a Bug"
    },
    "APPSTORE_TITLE": {
        "cn": "儿童水果猜猜乐",
        "en": "Kids Fruit Guess"
    },
    "APPSTORE_SUBTITLE": {
        "cn": "早教学习游戏",
        "en": "Early learning game"
    },
    "APPSTORE_PROMOTION": {
        "cn": "看图猜水果学习事物认识汉字",
        "en": "Look at pictures, guess fruits, learn things, understand Chinese characters"
    },
    "APPSTORE_KEYWORD": {
        "cn": "小孩玩的游戏大全,宝宝爱拼图,飞利浦儿童牙刷,认识动物医院小维智慧家庭,睡前音乐相册免费6岁,幼儿英语启蒙,掌上宝贝学英语,视通2,0,卫士,幼信通,汪汪队动画片,学声音,360电话,孩子长相预测",
        "en": "麦田认字软件,叫识字游戏,儿童益智,2kids学拼音,直映,学前数学,3岁宝宝爱学习汉字大赛,英大大智慧,画画大全,证券,幼儿园手工制作,悟空,认识字,童话故事成人,小鸡,在家早教音乐,巴巴熊儿歌多多"
    },
    "XIAOMI_KEYWORD": {
        "cn": "小孩玩的游戏大全 宝宝爱拼图 飞利浦儿童牙刷 认识动物医院小维智慧家庭 睡前音乐相册免费6岁 幼儿英语启蒙 掌上宝贝学英语 视通2 0 卫士 幼信通 汪汪队动画片 学声音 360电话 孩子长相预测",
        "en": "麦田认字软件 叫识字游戏 儿童益智 2kids学拼音 直映 学前数学 3岁宝宝爱学习汉字大赛 英大大智慧 画画大全 证券 幼儿园手工制作 悟空 认识字 童话故事成人 小鸡 在家早教音乐 巴巴熊儿歌多多"
    },
    "email": "chyfemail163@163.com",
    "software_url": "http://www.mooncore.cn",
    "privacy_url": "http://www.mooncore.cn/index/privacyPolicy_kidsgame.shtml",
    "support_url": "http://blog.sina.com.cn/s/blog_1736372fb0102xb49.html",
    "privacy_url_gp": "http://blog.sina.com.cn/s/blog_1736372fb0102xmbz.html",
    "sku_app": "moonma_caicaile"
}